{
  "experiment_id": "N0_centralized_vit_base_nwpu_20ep_lr5e5_aug_ls_cosine",
  "base_experiment_id": "N0_centralized_vit_base_nwpu",
  "output_suffix": "20ep_lr5e5_aug_ls_cosine",
  "dry_run": false,
  "model_name": "vit_base_patch16_224",
  "dataset": "NWPU-RESISC45",
  "num_classes": 45,
  "model_parameter_count": 85833261,
  "device": "cuda",
  "cuda_available": true,
  "amp_enabled": true,
  "epochs": 20,
  "actual_epochs_ran": 20,
  "batch_size": 16,
  "learning_rate": 5e-05,
  "weight_decay": 0.0001,
  "aug_policy": "remote_sensing_strong",
  "label_smoothing": 0.1,
  "scheduler": "cosine",
  "seed": 42,
  "best_epoch": 19,
  "best_val_accuracy": 0.9463492063492064,
  "final_train_accuracy": 0.9996825396825397,
  "final_val_accuracy": 0.946031746031746,
  "test_accuracy": 0.9464399092970521,
  "test_macro_f1": 0.9462451491201801,
  "test_weighted_f1": 0.9462451491201804,
  "total_training_time_seconds": 710.4329178000335,
  "training_time_sec": 710.4329178000335,
  "epoch_log_path": "E:\\VIT-FL\\privacy_fed_vit_rs\\results\\logs\\N0_centralized_vit_base_nwpu_20ep_lr5e5_aug_ls_cosine_epoch_log.csv",
  "checkpoint_path": "E:\\VIT-FL\\privacy_fed_vit_rs\\experiments\\centralized\\N0_centralized_vit_base_nwpu_20ep_lr5e5_aug_ls_cosine\\checkpoints\\best.pt",
  "best_checkpoint_path": "E:\\VIT-FL\\privacy_fed_vit_rs\\experiments\\centralized\\N0_centralized_vit_base_nwpu_20ep_lr5e5_aug_ls_cosine\\checkpoints\\best.pt",
  "last_checkpoint_path": "E:\\VIT-FL\\privacy_fed_vit_rs\\experiments\\centralized\\N0_centralized_vit_base_nwpu_20ep_lr5e5_aug_ls_cosine\\checkpoints\\last.pt",
  "resume_from": null,
  "test_metrics": {
    "loss": 0.8486330994024298,
    "accuracy": 0.9464399092970521,
    "macro_f1": 0.9462451491201801,
    "weighted_f1": 0.9462451491201804
  }
}